venvy/__init__.py
venvy/analysis.py
venvy/cleanup.py
venvy/cli.py
venvy/config.py
venvy/discovery.py
venvy/display.py
venvy/models.py
venvy/performance.py
venvy/registry.py
venvy/shell_integration.py
venvy/utils.py
venvy-0.2.0.dist-info/licenses/LICENSE
venvy-0.2.0.dist-info/METADATA
venvy-0.2.0.dist-info/WHEEL
venvy-0.2.0.dist-info/entry_points.txt
venvy-0.2.0.dist-info/top_level.txt
venvy-0.2.0.dist-info/RECORD
