Metadata-Version: 2.4
Name: venvy
Version: 0.2.0
Summary: Fast virtual environment manager with registry-based tracking
Author: Pranav Kumaar
License: MIT
Project-URL: Homepage, https://github.com/pranavkumaarofficial/venvy
Project-URL: Repository, https://github.com/pranavkumaarofficial/venvy
Project-URL: Documentation, https://github.com/pranavkumaarofficial/venvy#readme
Project-URL: Issues, https://github.com/pranavkumaarofficial/venvy/issues
Keywords: python,virtual-environment,venv,conda,environment-management
Classifier: Development Status :: 3 - Alpha
Classifier: Intended Audience :: Developers
Classifier: License :: OSI Approved :: MIT License
Classifier: Operating System :: OS Independent
Classifier: Programming Language :: Python :: 3
Classifier: Programming Language :: Python :: 3.8
Classifier: Programming Language :: Python :: 3.9
Classifier: Programming Language :: Python :: 3.10
Classifier: Programming Language :: Python :: 3.11
Classifier: Programming Language :: Python :: 3.12
Classifier: Topic :: Software Development :: Libraries :: Python Modules
Classifier: Topic :: System :: Systems Administration
Requires-Python: >=3.8
License-File: LICENSE
Requires-Dist: click>=8.0.0
Requires-Dist: rich>=13.0.0
Requires-Dist: psutil>=5.9.0
Requires-Dist: packaging>=21.0
Provides-Extra: dev
Requires-Dist: pytest>=7.0; extra == "dev"
Requires-Dist: pytest-cov>=4.0; extra == "dev"
Requires-Dist: black>=22.0; extra == "dev"
Requires-Dist: isort>=5.10; extra == "dev"
Requires-Dist: mypy>=1.0; extra == "dev"
Dynamic: license-file
